handcash_connect_sdk/__init__.py
handcash_connect_sdk/environments.py
handcash_connect_sdk/handcash_cloud_account.py
handcash_connect_sdk/profile.py
handcash_connect_sdk/wallet.py
handcash_connect_sdk/api/__init__.py
handcash_connect_sdk/api/handcash_connect_api_error.py
handcash_connect_sdk/api/handcash_connect_service.py
handcash_connect_sdk/api/http_request_factory.py
handcash_connect_sdk-0.1.2.dist-info/LICENSE
handcash_connect_sdk-0.1.2.dist-info/METADATA
handcash_connect_sdk-0.1.2.dist-info/WHEEL
handcash_connect_sdk-0.1.2.dist-info/top_level.txt
handcash_connect_sdk-0.1.2.dist-info/zip-safe
handcash_connect_sdk-0.1.2.dist-info/RECORD
