Metadata-Version: 2.1
Name: handcash-connect-sdk
Version: 0.1.2
Summary: handcash_connect_sdk - library for interacting with Handcash Connect API
Home-page: https://github.com/krzysiekfonal/handcash-connect-sdk-python
Author: Krzysztof Fonal
Author-email: krzysiekfonal@gmail.com
License: The Unlicense
Download-URL: https://github.com/krzysiekfonal/handcash-connect-sdk-python/releases/tag/v0.1.1
Keywords: api handcash
Platform: UNKNOWN
Classifier: Development Status :: 3 - Alpha
Classifier: License :: OSI Approved :: The Unlicense (Unlicense)
Classifier: Programming Language :: Python :: 3.8
Classifier: Topic :: Software Development :: Libraries :: Python Modules
Classifier: Intended Audience :: Developers
Requires-Dist: bitcoinx
Requires-Dist: requests
Requires-Dist: attr
